statementhelper/__init__.py
statementhelper-0.0.2.dist-info/LICENSE.txt
statementhelper-0.0.2.dist-info/METADATA
statementhelper-0.0.2.dist-info/WHEEL
statementhelper-0.0.2.dist-info/top_level.txt
statementhelper-0.0.2.dist-info/RECORD
