Metadata-Version: 2.1
Name: statementhelper
Version: 0.0.2
Summary: Definitions and examples for common Python statements.
Home-page: UNKNOWN
Author: Ryan Chou
Author-email: 
License: MIT
Keywords: help
Platform: UNKNOWN
Classifier: Development Status :: 5 - Production/Stable
Classifier: Intended Audience :: Education
Classifier: Operating System :: Microsoft :: Windows :: Windows 10
Classifier: License :: OSI Approved :: MIT License
Classifier: Programming Language :: Python :: 3
License-File: LICENSE.txt
